rainbowdoc/__init__.py
xremove/__init__.py
xremove/__prompt-init__.py
rainbowdoc-0.0.5.dist-info/METADATA
rainbowdoc-0.0.5.dist-info/WHEEL
rainbowdoc-0.0.5.dist-info/top_level.txt
rainbowdoc-0.0.5.dist-info/RECORD
